interval_counter.v
`timescale 1ns/1ns
module interval_counter(input clock,input reset,input enable,input interval_reset, input [15:0]interval, 
                      output switch_i_c, output [20:0] count_out);
    // intervalul o sa fie dat in minute, deci il inmultim cu 60
  reg [20:0] count_reg, count_next;
  reg switch_i_c_reg, switch_i_c_next;
  reg [20:0]interval_seconds_reg;

    always @(posedge clock or posedge reset) begin
        if(reset || interval_reset) begin
            count_reg <= 'b0;
            switch_i_c_reg<='b0;
            interval_seconds_reg<=60*interval;
        end else begin
            count_reg <= count_next;
            switch_i_c_reg <= switch_i_c_next;
        end
    end   

    always @* begin
        count_next = count_reg;
        switch_i_c_next = switch_i_c_reg;
        if(enable && !interval_reset) begin
            if(count_reg <= (interval_seconds_reg - 2) && count_reg >= (interval_seconds_reg - 6)) begin
                switch_i_c_next = 1'b1;
            end
            // aici se reseteaza contorul
            if(count_reg == (interval_seconds_reg - 1)) begin
                switch_i_c_next = 1'b0;
                count_next = 'b0;
            end else begin
                count_next = count_reg+1'b1;
            end
        end
    end

    assign switch_i_c = switch_i_c_reg;
    assign count_out = count_reg;
 
endmodule

`timescale 1ns/1ns
module tb_interval_counter();
  reg clock, reset, enable, interval_reset;
  reg [15:0]interval;
  wire switch_i_c;
  wire [20:0]count_out;
  
  interval_counter interval_counter_instance(.clock(clock),.reset(reset),.enable(enable),.interval_reset(interval_reset) ,.interval(interval),.switch_i_c(switch_i_c), .count_out(count_out));
  
  initial begin
    clock = 0;
    forever #2 clock = !clock;
  end
  initial begin
    interval=5'd10;
    reset = 1'b1;
    interval_reset = 1'b0;
    enable  = 1'b1;
    #3 reset = 1'b0;
    #200;
    interval_reset = 1'b1;
    #50;
    interval_reset = 1'b0;
    #10;
    enable = 1'b1;
    #20000;
    $finish();
  end
  initial begin
    $dumpfile("dump.vcd"); 
    $dumpvars;
  end
endmodule

food_counter.v
`timescale 1ns/1ns
module food_counter(input clock,input reset,input enable, input count_reset,  output switch_f_c, output [3:0] count_out);


  reg [3:0] count_reg, count_next;
  reg switch_f_c_reg, switch_f_c_next;
  localparam food_time = 10;

    always @(posedge clock or posedge reset) begin
        if(reset || count_reset) begin
            count_reg <= 'b0;
            switch_f_c_reg<='b0;
        end else begin
            count_reg <= count_next;
            switch_f_c_reg <= switch_f_c_next;
        end
    end   

    always @* begin
        count_next = count_reg;
        switch_f_c_next = switch_f_c_reg;
        if(enable && !count_reset) begin
            if(count_reg <= (food_time - 1) ) begin
                switch_f_c_next = 1'b1;
            end
            // aici se reseteaza contorul
            if(count_reg == (food_time)) begin
                switch_f_c_next = 1'b0;
                // problema apare aici din cauza lui count_reg care nu se reseteaza (nici nu pot sa-l resetez eu ca numara nonstop)
            end else begin
                count_next = count_reg+1'b1;
            end
        end
    end

    assign switch_f_c = switch_f_c_reg;
    assign count_out = count_reg;
 
endmodule

`timescale 1ns/1ns
module tb_food_counter();
  reg clock, reset, enable, count_reset;
  wire switch_f_c;
  wire [3:0]count_out;
  
  food_counter food_counter_instance(.clock(clock),.reset(reset),.enable(enable),.count_reset(count_reset),.switch_f_c(switch_f_c), .count_out(count_out));
  
  initial begin
    clock = 0;
    forever #2 clock = !clock;
  end
  initial begin
    reset = 1'b1;
    count_reset = 1'b0;
    enable  = 1'b1;
    #3 reset = 1'b0;
    #30
    count_reset = 1'b1;
    #30
    count_reset = 1'b0;
    #200;
    $finish();
  end
  initial begin
    $dumpfile("dump.vcd"); 
    $dumpvars;
  end
endmodule

option_fsm.v
`timescale 1ns/1ns
`define IDLE 3'b000
`define POUR_FOOD 3'b001
`define STOP_FOOD 3'b010
`define INTERVAL 3'b011
`define RESET 3'b100

module option_fsm(input clock, input reset, input fsm_enable, input [2:0] option, 
                    output count_enable, output count_reset, output interval_enable, output interval_reset);

reg [2:0] state_reg, state_next;
reg count_enable_reg, count_enable_next;
reg count_reset_reg, count_reset_next;
reg interval_enable_reg, interval_enable_next;
reg interval_reset_reg, interval_reset_next;
reg fsm_enable_reg, fsm_enable_next;


always @(posedge clock or posedge reset) begin
	if(reset) begin
		state_reg <= `RESET;
		count_enable_reg <= 1'b0;
		count_reset_reg <= 1'b0;
        interval_enable_reg <= 1'b0;
        interval_reset_reg <= 1'b0;
        fsm_enable_reg <= 1'b1; // button activ pe 1!!!!
	end
	else begin
		state_reg <= state_next;
		count_enable_reg <= count_enable_next;
		count_reset_reg <= count_reset_next;
        interval_enable_reg <= interval_enable_next;
        interval_reset_reg <= interval_reset_next;
        fsm_enable_reg <= fsm_enable_next;
	end
	
end

always @* begin 
	state_next = state_reg;
	count_enable_next = count_enable_reg;
	count_reset_next = count_reset_reg;
    interval_enable_next = interval_enable_reg;
    interval_reset_next = interval_reset_reg;
    fsm_enable_next = fsm_enable;

	case(state_reg)
	
		`RESET:	begin
			count_enable_next = 1'b0;
			count_reset_next = 1'b1;
            interval_enable_next = 1'b0;
            interval_reset_next = 1'b1;
			state_next = `IDLE;
		end
		`IDLE: begin
			if(fsm_enable) begin
                case(option)
                    `POUR_FOOD: state_next = `POUR_FOOD;
                    `STOP_FOOD: state_next = `STOP_FOOD;
                    `INTERVAL: state_next = `INTERVAL;
                endcase
			end
		end
		`POUR_FOOD: begin
			count_enable_next = 1'b1;
			count_reset_next = 1'b0;
            interval_enable_next = 1'b0;
            interval_reset_next = 1'b0;
			state_next = `IDLE;
		end
		`STOP_FOOD: begin
			count_enable_next = 1'b0;
			count_reset_next = 1'b1;
            interval_enable_next = 1'b0;
            interval_reset_next = 1'b1;
			state_next = `IDLE;
		end
		`INTERVAL: begin
			count_enable_next = 1'b0;
			count_reset_next = 1'b0;
            interval_enable_next = 1'b1;
            interval_reset_next = 1'b0;
			state_next = `IDLE;
		end
	
	endcase
	
	

end

assign count_enable = count_enable_reg;
assign count_reset = count_reset_reg;
assign interval_enable = interval_enable_reg;
assign interval_reset = interval_reset_reg;
  
endmodule 

`timescale 1ns/1ns

module tb_option_fsm();
  reg clock, reset, fsm_enable;
  reg [2:0] option;
  wire count_enable, count_reset, interval_enable, interval_reset;
  
  option_fsm option_fsm_instance(.clock(clock), .reset(reset), .fsm_enable(fsm_enable), .option(option), 
                .count_enable(count_enable), .count_reset(count_reset), .interval_enable(interval_enable), .interval_reset(interval_reset));
  
  initial begin 
    clock = 0;
    forever #10 clock = !clock;
  end
  
 
  initial begin

    reset = 1'b1;
    fsm_enable = 1'b1;
    option = 3'b000;
  	
    #100;
    reset = 1'b0;
    #100;

   
    option = 3'b001;
    #200; 
    fsm_enable = 1'b1;
    #200;
    fsm_enable = 1'b0;
    #200;
    // count_enable = 1, count_reset = 0, interval_enable = 0;
    #2000;

    
    option = 3'b010;
    #200; 
    fsm_enable = 1'b1;
    #200;
    fsm_enable = 1'b0;
    #200;
    // count_enable = 0, count_reset = 1, interval_enable = 0;
    #2000
   
    option = 3'b111;
    #80;
    option = 3'b101;
    #100;
    option = 3'b011;
    #200; 
    fsm_enable = 1'b1;
    #200;
    fsm_enable = 1'b0;
    #200;
    // count_enable = 0, count_reset = 0, interval_enable = 1;

    #2000;
 
    option = 3'b011;
    #100;
    option = 3'b001;
    #200; 
    fsm_enable = 1'b1;
    #200;
    fsm_enable = 1'b0;
    #200;

    #2000;
    // count_enable = 1, count_reset = 0, interval_enable = 0;

    option = 3'b010;
    #100;
    option = 3'b011;
    #200; 
    fsm_enable = 1'b0;
    #200;
    fsm_enable = 1'b1;
    #200;

    #2000;
    // count_enable = 1, count_reset = 0, interval_enable = 1;

    $finish();
  end
  
endmodule

adder.v
`timescale 1ns/1ns
module adder(input clock, reset,
            input [3:0] keyboard_digit, input digit_enable, 
            output [15:0] sum, output [15:0] prev_sum);

  reg [15:0] sum_reg, sum_next;
  reg [15:0] prev_sum_reg, prev_sum_next;

  always @(posedge clock or posedge reset) begin
    if(reset) begin
        sum_reg <= 0;
        prev_sum_reg <= 0;  
    end else begin
        sum_reg <= sum_next;
        prev_sum_reg <= prev_sum_next;
    end
  end

  always @* begin
    sum_next = sum_reg;
    prev_sum_next = prev_sum_reg;

    if(digit_enable == 1'b1) begin
        sum_next = sum_reg * 10 + keyboard_digit;
    end else begin
        prev_sum_next = prev_sum_reg * 10 + keyboard_digit;
    end
  end
  
  assign sum = sum_reg;
  assign prev_sum = prev_sum_reg;

endmodule

`timescale 1ns/1ns
module tb_adder();

reg clock, reset, digit_enable;
reg [3:0] keyboard_digit;
wire [15:0] sum, prev_sum;

adder alu(.clock(clock), .reset(reset), .keyboard_digit(keyboard_digit), .digit_enable(digit_enable), .sum(sum), .prev_sum(prev_sum));

initial begin
    clock = 0;
    forever #2 clock = !clock;
end

initial begin
    digit_enable = 1'b0;
    reset = 1'b1;
    #3 reset = 1'b0;
    #200;

    keyboard_digit  = 4'd4;
    #30;
    $display("Sum: %d, Prev_sum: %d", sum, prev_sum);
    keyboard_digit  = 4'd6;
    #30;
    $display("Sum: %d, Prev_sum: %d", sum, prev_sum);
    digit_enable = 1'b1;
    #4;
    $display("Sum: %d, Prev_sum: %d", sum, prev_sum);
    digit_enable = 1'b0;

    #30

    keyboard_digit  = 4'd3;
    #30;
    $display("Sum: %d, Prev_sum: %d", sum, prev_sum);
    keyboard_digit  = 4'd2;
    #30;
    $display("Sum: %d, Prev_sum: %d", sum, prev_sum);
    keyboard_digit  = 4'd7;
    #30;
    $display("Sum: %d, Prev_sum: %d", sum, prev_sum);
    digit_enable = 1'b1;
    #4;
    $display("Sum: %d, Prev_sum: %d", sum, prev_sum);
    digit_enable = 1'b0;
    #30
    
    keyboard_digit = 4'd5;
    #30;
    $display("Sum: %d, Prev_sum: %d", sum, prev_sum);
    digit_enable = 1'b1;
    #4;
    $display("Sum: %d, Prev_sum: %d", sum, prev_sum);
    digit_enable = 1'b0;
    #30
    $finish();
  end

endmodule

pf0.v
`timescale 1ns/1ns

module pet_feeder(input clock, reset, input [2:0]keyboard_option, input option_enable, 
    input [3:0]keyboard_digit, input digit_enable, output food_switch);
    wire count_enable, count_reset, interval_enable, interval_reset;
    wire [15:0]interval;
    wire new_clock_1Hz;
    wire switch_f_c, switch_i_c;
    wire [3:0]count_out_f_c;
    wire [20:0]count_out_i_c;

    localparam IDLE = 3'b000;
    localparam POUR_FOOD = 3'b001;
    localparam STOP_FOOD = 3'b010;
    localparam INTERVAL = 3'b011;
    localparam RESET = 3'b100;

    // clock dividerul este folosit intr-un scenariu realist in care procesorul are frecventa de 50Mhz si aceasta trebuie redusa la un 1Hz (pentru ca perioada unui clock sa fie de o secunda)
    //clock_divider#(.width(26), .MAX(50000000)) divider50MHz_1Hz(.clock(clock), .reset(reset), .new_clock(new_clock_1Hz));
    
    adder alu(.clock(clock), .reset(reset), .keyboard_digit(keyboard_digit), .digit_enable(digit_enable), .sum(interval));

    option_fsm option_fsm_inst(.clock(clock), .reset(reset), .fsm_enable(option_enable), .option(keyboard_option), 
                                .count_enable(count_enable), .count_reset(count_reset), .interval_enable(interval_enable), .interval_reset(interval_reset));

    food_counter food_counter_inst(.clock(clock), .reset(reset), .enable(count_enable), .count_reset(count_reset), 
                                .switch_f_c(switch_f_c), .count_out(count_out_f_c));
    
    interval_counter interval_counter_inst(.clock(clock), .reset(reset), .enable(interval_enable), .interval_reset(interval_reset), .interval(interval), 
                                .switch_i_c(switch_i_c), .count_out(count_out_i_c));


    assign food_switch = (keyboard_option==POUR_FOOD && switch_f_c) || (keyboard_option==INTERVAL && switch_i_c);

    

endmodule


`timescale 1ns/1ns
module tb_pet_feeder();
    reg clock, reset;
    reg [2:0]keyboard_option;
    reg [3:0]keyboard_digit;
    reg option_enable, digit_enable;
    wire food_switch;

    localparam IDLE = 3'b000;
    localparam POUR_FOOD = 3'b001;
    localparam STOP_FOOD = 3'b010;
    localparam INTERVAL = 3'b011;
    localparam RESET = 3'b100;

    pet_feeder pet_feeder_instance(
        .clock(clock), 
        .reset(reset), 
        .keyboard_option(keyboard_option), 
        .option_enable(option_enable), 
        .digit_enable(digit_enable), 
        .food_switch(food_switch)
    );

    initial begin
        clock = 0;
        forever #2 clock = !clock;  // Generarea semnalului de ceas
    end

    initial begin
        // Reset și inițializare
        reset = 1'b1;
        //fsm_enable = 1'b1;
        keyboard_option = IDLE;
        keyboard_digit = 4'b0;
        option_enable = 1'b0;
        digit_enable = 1'b0;
        #3 reset = 1'b0;

        // Test 1: POUR_FOOD
        #10;
        keyboard_option = POUR_FOOD;
        option_enable = 1'b1;
        #10 option_enable = 1'b0;
        #100;

        // Test 2: POUT_FOOD THEN STOP_FOOD
        option_enable = 1'b1;
        #8;
        option_enable = 1'b0;
        #10;
        keyboard_option = STOP_FOOD;
        option_enable = 1'b1;
        #10;
        option_enable = 1'b0;

        #100;

        $finish();
    end

    initial begin
        $dumpfile("dump.vcd"); 
        $dumpvars;  // Înregistrarea activităților pentru analiză
    end
endmodule

dump.vcd
$date
	Thu Jan 04 19:32:12 2024
$end
$version
	ModelSim Version 10.5b
$end
$timescale
	1ns
$end

$scope module tb_pet_feeder $end
$var parameter 3 ! IDLE $end
$var parameter 3 " POUR_FOOD $end
$var parameter 3 # STOP_FOOD $end
$var parameter 3 $ INTERVAL $end
$var parameter 3 % RESET $end
$var reg 1 & clock $end
$var reg 1 ' reset $end
$var reg 3 ( keyboard_option [2:0] $end
$var reg 4 ) keyboard_digit [3:0] $end
$var reg 1 * option_enable $end
$var reg 1 + digit_enable $end
$var wire 1 , food_switch $end

$scope module pet_feeder_instance $end
$var parameter 3 - IDLE $end
$var parameter 3 . POUR_FOOD $end
$var parameter 3 / STOP_FOOD $end
$var parameter 3 0 INTERVAL $end
$var parameter 3 1 RESET $end
$var wire 1 2 clock $end
$var wire 1 3 reset $end
$var wire 1 4 keyboard_option [2] $end
$var wire 1 5 keyboard_option [1] $end
$var wire 1 6 keyboard_option [0] $end
$var wire 1 7 option_enable $end
$var wire 1 8 keyboard_digit [3] $end
$var wire 1 9 keyboard_digit [2] $end
$var wire 1 : keyboard_digit [1] $end
$var wire 1 ; keyboard_digit [0] $end
$var wire 1 < digit_enable $end
$var wire 1 , food_switch $end
$var wire 1 = count_enable $end
$var wire 1 > count_reset $end
$var wire 1 ? interval_enable $end
$var wire 1 @ interval_reset $end
$var wire 1 A interval [15] $end
$var wire 1 B interval [14] $end
$var wire 1 C interval [13] $end
$var wire 1 D interval [12] $end
$var wire 1 E interval [11] $end
$var wire 1 F interval [10] $end
$var wire 1 G interval [9] $end
$var wire 1 H interval [8] $end
$var wire 1 I interval [7] $end
$var wire 1 J interval [6] $end
$var wire 1 K interval [5] $end
$var wire 1 L interval [4] $end
$var wire 1 M interval [3] $end
$var wire 1 N interval [2] $end
$var wire 1 O interval [1] $end
$var wire 1 P interval [0] $end
$var wire 1 Q new_clock_1Hz $end
$var wire 1 R switch_f_c $end
$var wire 1 S switch_i_c $end
$var wire 1 T count_out_f_c [3] $end
$var wire 1 U count_out_f_c [2] $end
$var wire 1 V count_out_f_c [1] $end
$var wire 1 W count_out_f_c [0] $end
$var wire 1 X count_out_i_c [20] $end
$var wire 1 Y count_out_i_c [19] $end
$var wire 1 Z count_out_i_c [18] $end
$var wire 1 [ count_out_i_c [17] $end
$var wire 1 \ count_out_i_c [16] $end
$var wire 1 ] count_out_i_c [15] $end
$var wire 1 ^ count_out_i_c [14] $end
$var wire 1 _ count_out_i_c [13] $end
$var wire 1 ` count_out_i_c [12] $end
$var wire 1 a count_out_i_c [11] $end
$var wire 1 b count_out_i_c [10] $end
$var wire 1 c count_out_i_c [9] $end
$var wire 1 d count_out_i_c [8] $end
$var wire 1 e count_out_i_c [7] $end
$var wire 1 f count_out_i_c [6] $end
$var wire 1 g count_out_i_c [5] $end
$var wire 1 h count_out_i_c [4] $end
$var wire 1 i count_out_i_c [3] $end
$var wire 1 j count_out_i_c [2] $end
$var wire 1 k count_out_i_c [1] $end
$var wire 1 l count_out_i_c [0] $end

$scope module alu $end
$var wire 1 2 clock $end
$var wire 1 3 reset $end
$var wire 1 8 keyboard_digit [3] $end
$var wire 1 9 keyboard_digit [2] $end
$var wire 1 : keyboard_digit [1] $end
$var wire 1 ; keyboard_digit [0] $end
$var wire 1 < digit_enable $end
$var wire 1 A sum [15] $end
$var wire 1 B sum [14] $end
$var wire 1 C sum [13] $end
$var wire 1 D sum [12] $end
$var wire 1 E sum [11] $end
$var wire 1 F sum [10] $end
$var wire 1 G sum [9] $end
$var wire 1 H sum [8] $end
$var wire 1 I sum [7] $end
$var wire 1 J sum [6] $end
$var wire 1 K sum [5] $end
$var wire 1 L sum [4] $end
$var wire 1 M sum [3] $end
$var wire 1 N sum [2] $end
$var wire 1 O sum [1] $end
$var wire 1 P sum [0] $end
$var wire 1 m prev_sum [15] $end
$var wire 1 n prev_sum [14] $end
$var wire 1 o prev_sum [13] $end
$var wire 1 p prev_sum [12] $end
$var wire 1 q prev_sum [11] $end
$var wire 1 r prev_sum [10] $end
$var wire 1 s prev_sum [9] $end
$var wire 1 t prev_sum [8] $end
$var wire 1 u prev_sum [7] $end
$var wire 1 v prev_sum [6] $end
$var wire 1 w prev_sum [5] $end
$var wire 1 x prev_sum [4] $end
$var wire 1 y prev_sum [3] $end
$var wire 1 z prev_sum [2] $end
$var wire 1 { prev_sum [1] $end
$var wire 1 | prev_sum [0] $end
$var reg 16 } sum_reg [15:0] $end
$var reg 16 ~ sum_next [15:0] $end
$var reg 16 !! prev_sum_reg [15:0] $end
$var reg 16 "! prev_sum_next [15:0] $end
$upscope $end

$scope module option_fsm_inst $end
$var wire 1 2 clock $end
$var wire 1 3 reset $end
$var wire 1 7 fsm_enable $end
$var wire 1 4 option [2] $end
$var wire 1 5 option [1] $end
$var wire 1 6 option [0] $end
$var wire 1 = count_enable $end
$var wire 1 > count_reset $end
$var wire 1 ? interval_enable $end
$var wire 1 @ interval_reset $end
$var reg 3 #! state_reg [2:0] $end
$var reg 3 $! state_next [2:0] $end
$var reg 1 %! count_enable_reg $end
$var reg 1 &! count_enable_next $end
$var reg 1 '! count_reset_reg $end
$var reg 1 (! count_reset_next $end
$var reg 1 )! interval_enable_reg $end
$var reg 1 *! interval_enable_next $end
$var reg 1 +! interval_reset_reg $end
$var reg 1 ,! interval_reset_next $end
$var reg 1 -! fsm_enable_reg $end
$var reg 1 .! fsm_enable_next $end
$upscope $end

$scope module food_counter_inst $end
$var parameter 32 /! food_time $end
$var wire 1 2 clock $end
$var wire 1 3 reset $end
$var wire 1 = enable $end
$var wire 1 > count_reset $end
$var wire 1 R switch_f_c $end
$var wire 1 T count_out [3] $end
$var wire 1 U count_out [2] $end
$var wire 1 V count_out [1] $end
$var wire 1 W count_out [0] $end
$var reg 4 0! count_reg [3:0] $end
$var reg 4 1! count_next [3:0] $end
$var reg 1 2! switch_f_c_reg $end
$var reg 1 3! switch_f_c_next $end
$upscope $end

$scope module interval_counter_inst $end
$var wire 1 2 clock $end
$var wire 1 3 reset $end
$var wire 1 ? enable $end
$var wire 1 @ interval_reset $end
$var wire 1 A interval [15] $end
$var wire 1 B interval [14] $end
$var wire 1 C interval [13] $end
$var wire 1 D interval [12] $end
$var wire 1 E interval [11] $end
$var wire 1 F interval [10] $end
$var wire 1 G interval [9] $end
$var wire 1 H interval [8] $end
$var wire 1 I interval [7] $end
$var wire 1 J interval [6] $end
$var wire 1 K interval [5] $end
$var wire 1 L interval [4] $end
$var wire 1 M interval [3] $end
$var wire 1 N interval [2] $end
$var wire 1 O interval [1] $end
$var wire 1 P interval [0] $end
$var wire 1 S switch_i_c $end
$var wire 1 X count_out [20] $end
$var wire 1 Y count_out [19] $end
$var wire 1 Z count_out [18] $end
$var wire 1 [ count_out [17] $end
$var wire 1 \ count_out [16] $end
$var wire 1 ] count_out [15] $end
$var wire 1 ^ count_out [14] $end
$var wire 1 _ count_out [13] $end
$var wire 1 ` count_out [12] $end
$var wire 1 a count_out [11] $end
$var wire 1 b count_out [10] $end
$var wire 1 c count_out [9] $end
$var wire 1 d count_out [8] $end
$var wire 1 e count_out [7] $end
$var wire 1 f count_out [6] $end
$var wire 1 g count_out [5] $end
$var wire 1 h count_out [4] $end
$var wire 1 i count_out [3] $end
$var wire 1 j count_out [2] $end
$var wire 1 k count_out [1] $end
$var wire 1 l count_out [0] $end
$var reg 21 4! count_reg [20:0] $end
$var reg 21 5! count_next [20:0] $end
$var reg 1 6! switch_i_c_reg $end
$var reg 1 7! switch_i_c_next $end
$var reg 21 8! interval_seconds_reg [20:0] $end
$upscope $end
$upscope $end
$upscope $end
$enddefinitions $end
#0
$dumpvars
0&
1'
b0 (
b0 )
0*
0+
b0 }
b0 ~
b0 !!
bx "!
b100 #!
b0 $!
0%!
0&!
0'!
1(!
0)!
0*!
0+!
1,!
1-!
0.!
b0 0!
b0 1!
02!
03!
b0 4!
b0 5!
06!
07!
bx 8!
b0 !
b1 "
b10 #
b11 $
b100 %
b0 -
b1 .
b10 /
b11 0
b100 1
b1010 /!
0,
0=
0>
0?
0@
0P
0O
0N
0M
0L
0K
0J
0I
0H
0G
0F
0E
0D
0C
0B
0A
zQ
0R
0S
0W
0V
0U
0T
0l
0k
0j
0i
0h
0g
0f
0e
0d
0c
0b
0a
0`
0_
0^
0]
0\
0[
0Z
0Y
0X
0<
07
06
05
04
13
02
z;
z:
z9
z8
0|
0{
0z
0y
0x
0w
0v
0u
0t
0s
0r
0q
0p
0o
0n
0m
$end
#2
1&
12
b0 8!
#3
0'
03
#4
0&
02
#6
1&
12
bx !!
b0 #!
1'!
1+!
0-!
x|
x{
xz
xy
xx
xw
xv
xu
xt
xs
xr
xq
xp
xo
xn
xm
1>
1@
#8
0&
02
#10
1&
12
#12
0&
02
#13
b1 (
1*
16
17
1.!
b1 $!
#14
1&
12
b1 #!
1-!
1&!
0(!
0,!
b0 $!
#16
0&
02
#18
1&
12
b0 #!
1%!
0'!
0+!
1=
0>
0@
13!
b1 1!
b1 $!
#20
0&
02
#22
1&
12
b1 #!
b1 0!
12!
1W
1R
1,
b10 1!
b0 $!
#23
0*
07
b1 $!
0.!
b0 $!
#24
0&
02
#26
1&
12
b0 #!
0-!
b10 0!
0W
1V
b11 1!
#28
0&
02
#30
1&
12
b11 0!
1W
b100 1!
#32
0&
02
#34
1&
12
b100 0!
0W
0V
1U
b101 1!
#36
0&
02
#38
1&
12
b101 0!
1W
b110 1!
#40
0&
02
#42
1&
12
b110 0!
0W
1V
b111 1!
#44
0&
02
#46
1&
12
b111 0!
1W
b1000 1!
#48
0&
02
#50
1&
12
b1000 0!
0W
0V
0U
1T
b1001 1!
#52
0&
02
#54
1&
12
b1001 0!
1W
03!
b1010 1!
#56
0&
02
#58
1&
12
b1010 0!
02!
0W
1V
0R
0,
b0 1!
#60
0&
02
#62
1&
12
b0 0!
0V
0T
13!
b1 1!
#64
0&
02
#66
1&
12
b1 0!
12!
1W
1R
1,
b10 1!
#68
0&
02
#70
1&
12
b10 0!
0W
1V
b11 1!
#72
0&
02
#74
1&
12
b11 0!
1W
b100 1!
#76
0&
02
#78
1&
12
b100 0!
0W
0V
1U
b101 1!
#80
0&
02
#82
1&
12
b101 0!
1W
b110 1!
#84
0&
02
#86
1&
12
b110 0!
0W
1V
b111 1!
#88
0&
02
#90
1&
12
b111 0!
1W
b1000 1!
#92
0&
02
#94
1&
12
b1000 0!
0W
0V
0U
1T
b1001 1!
#96
0&
02
#98
1&
12
b1001 0!
1W
03!
b1010 1!
#100
0&
02
#102
1&
12
b1010 0!
02!
0W
1V
0R
0,
b0 1!
#104
0&
02
#106
1&
12
b0 0!
0V
0T
13!
b1 1!
#108
0&
02
#110
1&
12
b1 0!
12!
1W
1R
1,
b10 1!
#112
0&
02
#114
1&
12
b10 0!
0W
1V
b11 1!
#116
0&
02
#118
1&
12
b11 0!
1W
b100 1!
#120
0&
02
#122
1&
12
b100 0!
0W
0V
1U
b101 1!
#123
1*
17
1.!
b1 $!
#124
0&
02
#126
1&
12
b1 #!
1-!
b101 0!
1W
b110 1!
b0 $!
#128
0&
02
#130
1&
12
b0 #!
b110 0!
0W
1V
b111 1!
b1 $!
#131
0*
07
b0 $!
0.!
#132
0&
02
#134
1&
12
0-!
b111 0!
1W
b1000 1!
#136
0&
02
#138
1&
12
b1000 0!
0W
0V
0U
1T
b1001 1!
#140
0&
02
#141
b10 (
1*
06
15
17
0,
1.!
b10 $!
#142
1&
12
b10 #!
1-!
b1001 0!
1W
03!
b1010 1!
0&!
1(!
1,!
b0 $!
#144
0&
02
#146
1&
12
b0 #!
0%!
1'!
1+!
b1010 0!
02!
0W
1V
0R
0=
1>
1@
b10 $!
#148
0&
02
#150
1&
12
b10 #!
b0 0!
0V
0T
b0 1!
b0 $!
#151
0*
07
b10 $!
0.!
b0 $!
#152
0&
02
#154
1&
12
b0 #!
0-!
