interval_counter.v
`timescale 1ns/1ns
module interval_counter(input clock,input reset,input enable,input interval_reset, input full_sensor, input [15:0]interval, 
                      output switch_i_c, output [20:0] count_out);
    // intervalul o sa fie dat in minute, deci il inmultim cu 60
  reg [20:0] count_reg, count_next;
  reg switch_i_c_reg, switch_i_c_next;
  reg [20:0]interval_seconds_reg;

    always @(posedge clock or posedge reset) begin
        if(reset || interval_reset || full_sensor) begin
            count_reg <= 'b0;
            switch_i_c_reg<='b0;
            interval_seconds_reg<=60*interval;
        end else begin
            count_reg <= count_next;
            switch_i_c_reg <= switch_i_c_next;
        end
    end   

    always @* begin
        count_next = count_reg;
        switch_i_c_next = switch_i_c_reg;
        if(enable && !interval_reset && !full_sensor) begin
            if(count_reg <= (interval_seconds_reg - 2) && count_reg >= (interval_seconds_reg - 6)) begin
                switch_i_c_next = 1'b1;
            end
            // aici se reseteaza contorul
            if(count_reg == (interval_seconds_reg - 1)) begin
                switch_i_c_next = 1'b0;
                count_next = 'b0;
            end else begin
                count_next = count_reg+1'b1;
            end
        end
    end

    assign switch_i_c = switch_i_c_reg;
    assign count_out = count_reg;
 
endmodule

`timescale 1ns/1ns
module tb_interval_counter();
  reg clock, reset, enable, interval_reset, full_sensor;
  reg [15:0]interval;
  wire switch_i_c;
  wire [20:0]count_out;
  
  interval_counter interval_counter_instance(.clock(clock),.reset(reset),.enable(enable),.interval_reset(interval_reset), .full_sensor(full_sensor) ,.interval(interval),.switch_i_c(switch_i_c), .count_out(count_out));
  
  initial begin
    clock = 0;
    forever #2 clock = !clock;
  end
  initial begin
    full_sensor = 1'b0;
    interval=5'd3;
    reset = 1'b1;
    interval_reset = 1'b0;
    enable  = 1'b1;
    #3 reset = 1'b0;
    #200;
    interval_reset = 1'b1;
    #50;
    interval_reset = 1'b0;
    #10;
    enable = 1'b1;
    #1000;
    full_sensor = 1'b1;
    #1000;
    full_sensor = 1'b0;
    #20000;
    $finish();
  end
  initial begin
    $dumpfile("dump.vcd"); 
    $dumpvars;
  end
endmodule

dump.vcd
$date
	Fri Jan 05 20:19:01 2024
$end
$version
	ModelSim Version 10.5b
$end
$timescale
	1ns
$end

$scope module tb_interval_counter $end
$var reg 1 ! clock $end
$var reg 1 " reset $end
$var reg 1 # enable $end
$var reg 1 $ interval_reset $end
$var reg 1 % full_sensor $end
$var reg 16 & interval [15:0] $end
$var wire 1 ' switch_i_c $end
$var wire 1 ( count_out [20] $end
$var wire 1 ) count_out [19] $end
$var wire 1 * count_out [18] $end
$var wire 1 + count_out [17] $end
$var wire 1 , count_out [16] $end
$var wire 1 - count_out [15] $end
$var wire 1 . count_out [14] $end
$var wire 1 / count_out [13] $end
$var wire 1 0 count_out [12] $end
$var wire 1 1 count_out [11] $end
$var wire 1 2 count_out [10] $end
$var wire 1 3 count_out [9] $end
$var wire 1 4 count_out [8] $end
$var wire 1 5 count_out [7] $end
$var wire 1 6 count_out [6] $end
$var wire 1 7 count_out [5] $end
$var wire 1 8 count_out [4] $end
$var wire 1 9 count_out [3] $end
$var wire 1 : count_out [2] $end
$var wire 1 ; count_out [1] $end
$var wire 1 < count_out [0] $end

$scope module interval_counter_instance $end
$var wire 1 = clock $end
$var wire 1 > reset $end
$var wire 1 ? enable $end
$var wire 1 @ interval_reset $end
$var wire 1 A full_sensor $end
$var wire 1 B interval [15] $end
$var wire 1 C interval [14] $end
$var wire 1 D interval [13] $end
$var wire 1 E interval [12] $end
$var wire 1 F interval [11] $end
$var wire 1 G interval [10] $end
$var wire 1 H interval [9] $end
$var wire 1 I interval [8] $end
$var wire 1 J interval [7] $end
$var wire 1 K interval [6] $end
$var wire 1 L interval [5] $end
$var wire 1 M interval [4] $end
$var wire 1 N interval [3] $end
$var wire 1 O interval [2] $end
$var wire 1 P interval [1] $end
$var wire 1 Q interval [0] $end
$var wire 1 ' switch_i_c $end
$var wire 1 ( count_out [20] $end
$var wire 1 ) count_out [19] $end
$var wire 1 * count_out [18] $end
$var wire 1 + count_out [17] $end
$var wire 1 , count_out [16] $end
$var wire 1 - count_out [15] $end
$var wire 1 . count_out [14] $end
$var wire 1 / count_out [13] $end
$var wire 1 0 count_out [12] $end
$var wire 1 1 count_out [11] $end
$var wire 1 2 count_out [10] $end
$var wire 1 3 count_out [9] $end
$var wire 1 4 count_out [8] $end
$var wire 1 5 count_out [7] $end
$var wire 1 6 count_out [6] $end
$var wire 1 7 count_out [5] $end
$var wire 1 8 count_out [4] $end
$var wire 1 9 count_out [3] $end
$var wire 1 : count_out [2] $end
$var wire 1 ; count_out [1] $end
$var wire 1 < count_out [0] $end
$var reg 21 R count_reg [20:0] $end
$var reg 21 S count_next [20:0] $end
$var reg 1 T switch_i_c_reg $end
$var reg 1 U switch_i_c_next $end
$var reg 21 V interval_seconds_reg [20:0] $end
$upscope $end
$upscope $end
$enddefinitions $end
#0
$dumpvars
0!
1"
1#
0$
0%
b11 &
b0 R
b1 S
0T
0U
b10110100 V
0'
0<
0;
0:
09
08
07
06
05
04
03
02
01
00
0/
0.
0-
0,
0+
0*
0)
0(
1Q
1P
0O
0N
0M
0L
0K
0J
0I
0H
0G
0F
0E
0D
0C
0B
0A
0@
1?
1>
0=
$end
#2
1!
1=
#3
0"
0>
#4
0!
0=
#6
1!
1=
b1 R
1<
b10 S
#8
0!
0=
#10
1!
1=
b10 R
0<
1;
b11 S
#12
0!
0=
#14
1!
1=
b11 R
1<
b100 S
#16
0!
0=
#18
1!
1=
b100 R
0<
0;
1:
b101 S
#20
0!
0=
#22
1!
1=
b101 R
1<
b110 S
#24
0!
0=
#26
1!
1=
b110 R
0<
1;
b111 S
#28
0!
0=
#30
1!
1=
b111 R
1<
b1000 S
#32
0!
0=
#34
1!
1=
b1000 R
0<
0;
0:
19
b1001 S
#36
0!
0=
#38
1!
1=
b1001 R
1<
b1010 S
#40
0!
0=
#42
1!
1=
b1010 R
0<
1;
b1011 S
#44
0!
0=
#46
1!
1=
b1011 R
1<
b1100 S
#48
0!
0=
#50
1!
1=
b1100 R
0<
0;
1:
b1101 S
#52
0!
0=
#54
1!
1=
b1101 R
1<
b1110 S
#56
0!
0=
#58
1!
1=
b1110 R
0<
1;
b1111 S
#60
0!
0=
#62
1!
1=
b1111 R
1<
b10000 S
#64
0!
0=
#66
1!
1=
b10000 R
0<
0;
0:
09
18
b10001 S
#68
0!
0=
#70
1!
1=
b10001 R
1<
b10010 S
#72
0!
0=
#74
1!
1=
b10010 R
0<
1;
b10011 S
#76
0!
0=
#78
1!
1=
b10011 R
1<
b10100 S
#80
0!
0=
#82
1!
1=
b10100 R
0<
0;
1:
b10101 S
#84
0!
0=
#86
1!
1=
b10101 R
1<
b10110 S
#88
0!
0=
#90
1!
1=
b10110 R
0<
1;
b10111 S
#92
0!
0=
#94
1!
1=
b10111 R
1<
b11000 S
#96
0!
0=
#98
1!
1=
b11000 R
0<
0;
0:
19
b11001 S
#100
0!
0=
#102
1!
1=
b11001 R
1<
b11010 S
#104
0!
0=
#106
1!
1=
b11010 R
0<
1;
b11011 S
#108
0!
0=
#110
1!
1=
b11011 R
1<
b11100 S
#112
0!
0=
#114
1!
1=
b11100 R
0<
0;
1:
b11101 S
#116
0!
0=
#118
1!
1=
b11101 R
1<
b11110 S
#120
0!
0=
#122
1!
1=
b11110 R
0<
1;
b11111 S
#124
0!
0=
#126
1!
1=
b11111 R
1<
b100000 S
#128
0!
0=
#130
1!
1=
b100000 R
0<
0;
0:
09
08
17
b100001 S
#132
0!
0=
#134
1!
1=
b100001 R
1<
b100010 S
#136
0!
0=
#138
1!
1=
b100010 R
0<
1;
b100011 S
#140
0!
0=
#142
1!
1=
b100011 R
1<
b100100 S
#144
0!
0=
#146
1!
1=
b100100 R
0<
0;
1:
b100101 S
#148
0!
0=
#150
1!
1=
b100101 R
1<
b100110 S
#152
0!
0=
#154
1!
1=
b100110 R
0<
1;
b100111 S
#156
0!
0=
#158
1!
1=
b100111 R
1<
b101000 S
#160
0!
0=
#162
1!
1=
b101000 R
0<
0;
0:
19
b101001 S
#164
0!
0=
#166
1!
1=
b101001 R
1<
b101010 S
#168
0!
0=
#170
1!
1=
b101010 R
0<
1;
b101011 S
#172
0!
0=
#174
1!
1=
b101011 R
1<
b101100 S
#176
0!
0=
#178
1!
1=
b101100 R
0<
0;
1:
b101101 S
#180
0!
0=
#182
1!
1=
b101101 R
1<
b101110 S
#184
0!
0=
#186
1!
1=
b101110 R
0<
1;
b101111 S
#188
0!
0=
#190
1!
1=
b101111 R
1<
b110000 S
#192
0!
0=
#194
1!
1=
b110000 R
0<
0;
0:
09
18
b110001 S
#196
0!
0=
#198
1!
1=
b110001 R
1<
b110010 S
#200
0!
0=
#202
1!
1=
b110010 R
0<
1;
b110011 S
#203
1$
1@
b110010 S
#204
0!
0=
#206
1!
1=
b0 R
0;
08
07
b0 S
#208
0!
0=
#210
1!
1=
#212
0!
0=
#214
1!
1=
#216
0!
0=
#218
1!
1=
#220
0!
0=
#222
1!
1=
#224
0!
0=
#226
1!
1=
#228
0!
0=
#230
1!
1=
#232
0!
0=
#234
1!
1=
#236
0!
0=
#238
1!
1=
#240
0!
0=
#242
1!
1=
#244
0!
0=
#246
1!
1=
#248
0!
0=
#250
1!
1=
#252
0!
0=
#253
0$
0@
b1 S
#254
1!
1=
b1 R
1<
b10 S
#256
0!
0=
#258
1!
1=
b10 R
0<
1;
b11 S
#260
0!
0=
#262
1!
1=
b11 R
1<
b100 S
#264
0!
0=
#266
1!
1=
b100 R
0<
0;
1:
b101 S
#268
0!
0=
#270
1!
1=
b101 R
1<
b110 S
#272
0!
0=
#274
1!
1=
b110 R
0<
1;
b111 S
#276
0!
0=
#278
1!
1=
b111 R
1<
b1000 S
#280
0!
0=
#282
1!
1=
b1000 R
0<
0;
0:
19
b1001 S
#284
0!
0=
#286
1!
1=
b1001 R
1<
b1010 S
#288
0!
0=
#290
1!
1=
b1010 R
0<
1;
b1011 S
#292
0!
0=
#294
1!
1=
b1011 R
1<
b1100 S
#296
0!
0=
#298
1!
1=
b1100 R
0<
0;
1:
b1101 S
#300
0!
0=
#302
1!
1=
b1101 R
1<
b1110 S
#304
0!
0=
#306
1!
1=
b1110 R
0<
1;
b1111 S
#308
0!
0=
#310
1!
1=
b1111 R
1<
b10000 S
#312
0!
0=
#314
1!
1=
b10000 R
0<
0;
0:
09
18
b10001 S
#316
0!
0=
#318
1!
1=
b10001 R
1<
b10010 S
#320
0!
0=
#322
1!
1=
b10010 R
0<
1;
b10011 S
#324
0!
0=
#326
1!
1=
b10011 R
1<
b10100 S
#328
0!
0=
#330
1!
1=
b10100 R
0<
0;
1:
b10101 S
#332
0!
0=
#334
1!
1=
b10101 R
1<
b10110 S
#336
0!
0=
#338
1!
1=
b10110 R
0<
1;
b10111 S
#340
0!
0=
#342
1!
1=
b10111 R
1<
b11000 S
#344
0!
0=
#346
1!
1=
b11000 R
0<
0;
0:
19
b11001 S
#348
0!
0=
#350
1!
1=
b11001 R
1<
b11010 S
#352
0!
0=
#354
1!
1=
b11010 R
0<
1;
b11011 S
#356
0!
0=
#358
1!
1=
b11011 R
1<
b11100 S
#360
0!
0=
#362
1!
1=
b11100 R
0<
0;
1:
b11101 S
#364
0!
0=
#366
1!
1=
b11101 R
1<
b11110 S
#368
0!
0=
#370
1!
1=
b11110 R
0<
1;
b11111 S
#372
0!
0=
#374
1!
1=
b11111 R
1<
b100000 S
#376
0!
0=
#378
1!
1=
b100000 R
0<
0;
0:
09
08
17
b100001 S
#380
0!
0=
#382
1!
1=
b100001 R
1<
b100010 S
#384
0!
0=
#386
1!
1=
b100010 R
0<
1;
b100011 S
#388
0!
0=
#390
1!
1=
b100011 R
1<
b100100 S
#392
0!
0=
#394
1!
1=
b100100 R
0<
0;
1:
b100101 S
#396
0!
0=
#398
1!
1=
b100101 R
1<
b100110 S
#400
0!
0=
#402
1!
1=
b100110 R
0<
1;
b100111 S
#404
0!
0=
#406
1!
1=
b100111 R
1<
b101000 S
#408
0!
0=
#410
1!
1=
b101000 R
0<
0;
0:
19
b101001 S
#412
0!
0=
#414
1!
1=
b101001 R
1<
b101010 S
#416
0!
0=
#418
1!
1=
b101010 R
0<
1;
b101011 S
#420
0!
0=
#422
1!
1=
b101011 R
1<
b101100 S
#424
0!
0=
#426
1!
1=
b101100 R
0<
0;
1:
b101101 S
#428
0!
0=
#430
1!
1=
b101101 R
1<
b101110 S
#432
0!
0=
#434
1!
1=
b101110 R
0<
1;
b101111 S
#436
0!
0=
#438
1!
1=
b101111 R
1<
b110000 S
#440
0!
0=
#442
1!
1=
b110000 R
0<
0;
0:
09
18
b110001 S
#444
0!
0=
#446
1!
1=
b110001 R
1<
b110010 S
#448
0!
0=
#450
1!
1=
b110010 R
0<
1;
b110011 S
#452
0!
0=
#454
1!
1=
b110011 R
1<
b110100 S
#456
0!
0=
#458
1!
1=
b110100 R
0<
0;
1:
b110101 S
#460
0!
0=
#462
1!
1=
b110101 R
1<
b110110 S
#464
0!
0=
#466
1!
1=
b110110 R
0<
1;
b110111 S
#468
0!
0=
#470
1!
1=
b110111 R
1<
b111000 S
#472
0!
0=
#474
1!
1=
b111000 R
0<
0;
0:
19
b111001 S
#476
0!
0=
#478
1!
1=
b111001 R
1<
b111010 S
#480
0!
0=
#482
1!
1=
b111010 R
0<
1;
b111011 S
#484
0!
0=
#486
1!
1=
b111011 R
1<
b111100 S
#488
0!
0=
#490
1!
1=
b111100 R
0<
0;
1:
b111101 S
#492
0!
0=
#494
1!
1=
b111101 R
1<
b111110 S
#496
0!
0=
#498
1!
1=
b111110 R
0<
1;
b111111 S
#500
0!
0=
#502
1!
1=
b111111 R
1<
b1000000 S
#504
0!
0=
#506
1!
1=
b1000000 R
0<
0;
0:
09
08
07
16
b1000001 S
#508
0!
0=
#510
1!
1=
b1000001 R
1<
b1000010 S
#512
0!
0=
#514
1!
1=
b1000010 R
0<
1;
b1000011 S
#516
0!
0=
#518
1!
1=
b1000011 R
1<
b1000100 S
#520
0!
0=
#522
1!
1=
b1000100 R
0<
0;
1:
b1000101 S
#524
0!
0=
#526
1!
1=
b1000101 R
1<
b1000110 S
#528
0!
0=
#530
1!
1=
b1000110 R
0<
1;
b1000111 S
#532
0!
0=
#534
1!
1=
b1000111 R
1<
b1001000 S
#536
0!
0=
#538
1!
1=
b1001000 R
0<
0;
0:
19
b1001001 S
#540
0!
0=
#542
1!
1=
b1001001 R
1<
b1001010 S
#544
0!
0=
#546
1!
1=
b1001010 R
0<
1;
b1001011 S
#548
0!
0=
#550
1!
1=
b1001011 R
1<
b1001100 S
#552
0!
0=
#554
1!
1=
b1001100 R
0<
0;
1:
b1001101 S
#556
0!
0=
#558
1!
1=
b1001101 R
1<
b1001110 S
#560
0!
0=
#562
1!
1=
b1001110 R
0<
1;
b1001111 S
#564
0!
0=
#566
1!
1=
b1001111 R
1<
b1010000 S
#568
0!
0=
#570
1!
1=
b1010000 R
0<
0;
0:
09
18
b1010001 S
#572
0!
0=
#574
1!
1=
b1010001 R
1<
b1010010 S
#576
0!
0=
#578
1!
1=
b1010010 R
0<
1;
b1010011 S
#580
0!
0=
#582
1!
1=
b1010011 R
1<
b1010100 S
#584
0!
0=
#586
1!
1=
b1010100 R
0<
0;
1:
b1010101 S
#588
0!
0=
#590
1!
1=
b1010101 R
1<
b1010110 S
#592
0!
0=
#594
1!
1=
b1010110 R
0<
1;
b1010111 S
#596
0!
0=
#598
1!
1=
b1010111 R
1<
b1011000 S
#600
0!
0=
#602
1!
1=
b1011000 R
0<
0;
0:
19
b1011001 S
#604
0!
0=
#606
1!
1=
b1011001 R
1<
b1011010 S
#608
0!
0=
#610
1!
1=
b1011010 R
0<
1;
b1011011 S
#612
0!
0=
#614
1!
1=
b1011011 R
1<
b1011100 S
#616
0!
0=
#618
1!
1=
b1011100 R
0<
0;
1:
b1011101 S
#620
0!
0=
#622
1!
1=
b1011101 R
1<
b1011110 S
#624
0!
0=
#626
1!
1=
b1011110 R
0<
1;
b1011111 S
#628
0!
0=
#630
1!
1=
b1011111 R
1<
b1100000 S
#632
0!
0=
#634
1!
1=
b1100000 R
0<
0;
0:
09
08
17
b1100001 S
#636
0!
0=
#638
1!
1=
b1100001 R
1<
b1100010 S
#640
0!
0=
#642
1!
1=
b1100010 R
0<
1;
b1100011 S
#644
0!
0=
#646
1!
1=
b1100011 R
1<
b1100100 S
#648
0!
0=
#650
1!
1=
b1100100 R
0<
0;
1:
b1100101 S
#652
0!
0=
#654
1!
1=
b1100101 R
1<
b1100110 S
#656
0!
0=
#658
1!
1=
b1100110 R
0<
1;
b1100111 S
#660
0!
0=
#662
1!
1=
b1100111 R
1<
b1101000 S
#664
0!
0=
#666
1!
1=
b1101000 R
0<
0;
0:
19
b1101001 S
#668
0!
0=
#670
1!
1=
b1101001 R
1<
b1101010 S
#672
0!
0=
#674
1!
1=
b1101010 R
0<
1;
b1101011 S
#676
0!
0=
#678
1!
1=
b1101011 R
1<
b1101100 S
#680
0!
0=
#682
1!
1=
b1101100 R
0<
0;
1:
b1101101 S
#684
0!
0=
#686
1!
1=
b1101101 R
1<
b1101110 S
#688
0!
0=
#690
1!
1=
b1101110 R
0<
1;
b1101111 S
#692
0!
0=
#694
1!
1=
b1101111 R
1<
b1110000 S
#696
0!
0=
#698
1!
1=
b1110000 R
0<
0;
0:
09
18
b1110001 S
#700
0!
0=
#702
1!
1=
b1110001 R
1<
b1110010 S
#704
0!
0=
#706
1!
1=
b1110010 R
0<
1;
b1110011 S
#708
0!
0=
#710
1!
1=
b1110011 R
1<
b1110100 S
#712
0!
0=
#714
1!
1=
b1110100 R
0<
0;
1:
b1110101 S
#716
0!
0=
#718
1!
1=
b1110101 R
1<
b1110110 S
#720
0!
0=
#722
1!
1=
b1110110 R
0<
1;
b1110111 S
#724
0!
0=
#726
1!
1=
b1110111 R
1<
b1111000 S
#728
0!
0=
#730
1!
1=
b1111000 R
0<
0;
0:
19
b1111001 S
#732
0!
0=
#734
1!
1=
b1111001 R
1<
b1111010 S
#736
0!
0=
#738
1!
1=
b1111010 R
0<
1;
b1111011 S
#740
0!
0=
#742
1!
1=
b1111011 R
1<
b1111100 S
#744
0!
0=
#746
1!
1=
b1111100 R
0<
0;
1:
b1111101 S
#748
0!
0=
#750
1!
1=
b1111101 R
1<
b1111110 S
#752
0!
0=
#754
1!
1=
b1111110 R
0<
1;
b1111111 S
#756
0!
0=
#758
1!
1=
b1111111 R
1<
b10000000 S
#760
0!
0=
#762
1!
1=
b10000000 R
0<
0;
0:
09
08
07
06
15
b10000001 S
#764
0!
0=
#766
1!
1=
b10000001 R
1<
b10000010 S
#768
0!
0=
#770
1!
1=
b10000010 R
0<
1;
b10000011 S
#772
0!
0=
#774
1!
1=
b10000011 R
1<
b10000100 S
#776
0!
0=
#778
1!
1=
b10000100 R
0<
0;
1:
b10000101 S
#780
0!
0=
#782
1!
1=
b10000101 R
1<
b10000110 S
#784
0!
0=
#786
1!
1=
b10000110 R
0<
1;
b10000111 S
#788
0!
0=
#790
1!
1=
b10000111 R
1<
b10001000 S
#792
0!
0=
#794
1!
1=
b10001000 R
0<
0;
0:
19
b10001001 S
#796
0!
0=
#798
1!
1=
b10001001 R
1<
b10001010 S
#800
0!
0=
#802
1!
1=
b10001010 R
0<
1;
b10001011 S
#804
0!
0=
#806
1!
1=
b10001011 R
1<
b10001100 S
#808
0!
0=
#810
1!
1=
b10001100 R
0<
0;
1:
b10001101 S
#812
0!
0=
#814
1!
1=
b10001101 R
1<
b10001110 S
#816
0!
0=
#818
1!
1=
b10001110 R
0<
1;
b10001111 S
#820
0!
0=
#822
1!
1=
b10001111 R
1<
b10010000 S
#824
0!
0=
#826
1!
1=
b10010000 R
0<
0;
0:
09
18
b10010001 S
#828
0!
0=
#830
1!
1=
b10010001 R
1<
b10010010 S
#832
0!
0=
#834
1!
1=
b10010010 R
0<
1;
b10010011 S
#836
0!
0=
#838
1!
1=
b10010011 R
1<
b10010100 S
#840
0!
0=
#842
1!
1=
b10010100 R
0<
0;
1:
b10010101 S
#844
0!
0=
#846
1!
1=
b10010101 R
1<
b10010110 S
#848
0!
0=
#850
1!
1=
b10010110 R
0<
1;
b10010111 S
#852
0!
0=
#854
1!
1=
b10010111 R
1<
b10011000 S
#856
0!
0=
#858
1!
1=
b10011000 R
0<
0;
0:
19
b10011001 S
#860
0!
0=
#862
1!
1=
b10011001 R
1<
b10011010 S
#864
0!
0=
#866
1!
1=
b10011010 R
0<
1;
b10011011 S
#868
0!
0=
#870
1!
1=
b10011011 R
1<
b10011100 S
#872
0!
0=
#874
1!
1=
b10011100 R
0<
0;
1:
b10011101 S
#876
0!
0=
#878
1!
1=
b10011101 R
1<
b10011110 S
#880
0!
0=
#882
1!
1=
b10011110 R
0<
1;
b10011111 S
#884
0!
0=
#886
1!
1=
b10011111 R
1<
b10100000 S
#888
0!
0=
#890
1!
1=
b10100000 R
0<
0;
0:
09
08
17
b10100001 S
#892
0!
0=
#894
1!
1=
b10100001 R
1<
b10100010 S
#896
0!
0=
#898
1!
1=
b10100010 R
0<
1;
b10100011 S
#900
0!
0=
#902
1!
1=
b10100011 R
1<
b10100100 S
#904
0!
0=
#906
1!
1=
b10100100 R
0<
0;
1:
b10100101 S
#908
0!
0=
#910
1!
1=
b10100101 R
1<
b10100110 S
#912
0!
0=
#914
1!
1=
b10100110 R
0<
1;
b10100111 S
#916
0!
0=
#918
1!
1=
b10100111 R
1<
b10101000 S
#920
0!
0=
#922
1!
1=
b10101000 R
0<
0;
0:
19
b10101001 S
#924
0!
0=
#926
1!
1=
b10101001 R
1<
b10101010 S
#928
0!
0=
#930
1!
1=
b10101010 R
0<
1;
b10101011 S
#932
0!
0=
#934
1!
1=
b10101011 R
1<
b10101100 S
#936
0!
0=
#938
1!
1=
b10101100 R
0<
0;
1:
b10101101 S
#940
0!
0=
#942
1!
1=
b10101101 R
1<
b10101110 S
#944
0!
0=
#946
1!
1=
b10101110 R
0<
1;
1U
b10101111 S
#948
0!
0=
#950
1!
1=
b10101111 R
1T
1<
1'
b10110000 S
#952
0!
0=
#954
1!
1=
b10110000 R
0<
0;
0:
09
18
b10110001 S
#956
0!
0=
#958
1!
1=
b10110001 R
1<
b10110010 S
#960
0!
0=
#962
1!
1=
b10110010 R
0<
1;
b10110011 S
#964
0!
0=
#966
1!
1=
b10110011 R
1<
0U
b0 S
#968
0!
0=
#970
1!
1=
b0 R
0T
0<
0;
08
07
05
0'
b1 S
#972
0!
0=
#974
1!
1=
b1 R
1<
b10 S
#976
0!
0=
#978
1!
1=
b10 R
0<
1;
b11 S
#980
0!
0=
#982
1!
1=
b11 R
1<
b100 S
#984
0!
0=
#986
1!
1=
b100 R
0<
0;
1:
b101 S
#988
0!
0=
#990
1!
1=
b101 R
1<
b110 S
#992
0!
0=
#994
1!
1=
b110 R
0<
1;
b111 S
#996
0!
0=
#998
1!
1=
b111 R
1<
b1000 S
#1000
0!
0=
#1002
1!
1=
b1000 R
0<
0;
0:
19
b1001 S
#1004
0!
0=
#1006
1!
1=
b1001 R
1<
b1010 S
#1008
0!
0=
#1010
1!
1=
b1010 R
0<
1;
b1011 S
#1012
0!
0=
#1014
1!
1=
b1011 R
1<
b1100 S
#1016
0!
0=
#1018
1!
1=
b1100 R
0<
0;
1:
b1101 S
#1020
0!
0=
#1022
1!
1=
b1101 R
1<
b1110 S
#1024
0!
0=
#1026
1!
1=
b1110 R
0<
1;
b1111 S
#1028
0!
0=
#1030
1!
1=
b1111 R
1<
b10000 S
#1032
0!
0=
#1034
1!
1=
b10000 R
0<
0;
0:
09
18
b10001 S
#1036
0!
0=
#1038
1!
1=
b10001 R
1<
b10010 S
#1040
0!
0=
#1042
1!
1=
b10010 R
0<
1;
b10011 S
#1044
0!
0=
#1046
1!
1=
b10011 R
1<
b10100 S
#1048
0!
0=
#1050
1!
1=
b10100 R
0<
0;
1:
b10101 S
#1052
0!
0=
#1054
1!
1=
b10101 R
1<
b10110 S
#1056
0!
0=
#1058
1!
1=
b10110 R
0<
1;
b10111 S
#1060
0!
0=
#1062
1!
1=
b10111 R
1<
b11000 S
#1064
0!
0=
#1066
1!
1=
b11000 R
0<
0;
0:
19
b11001 S
#1068
0!
0=
#1070
1!
1=
b11001 R
1<
b11010 S
#1072
0!
0=
#1074
1!
1=
b11010 R
0<
1;
b11011 S
#1076
0!
0=
#1078
1!
1=
b11011 R
1<
b11100 S
#1080
0!
0=
#1082
1!
1=
b11100 R
0<
0;
1:
b11101 S
#1084
0!
0=
#1086
1!
1=
b11101 R
1<
b11110 S
#1088
0!
0=
#1090
1!
1=
b11110 R
0<
1;
b11111 S
#1092
0!
0=
#1094
1!
1=
b11111 R
1<
b100000 S
#1096
0!
0=
#1098
1!
1=
b100000 R
0<
0;
0:
09
08
17
b100001 S
#1100
0!
0=
#1102
1!
1=
b100001 R
1<
b100010 S
#1104
0!
0=
#1106
1!
1=
b100010 R
0<
1;
b100011 S
#1108
0!
0=
#1110
1!
1=
b100011 R
1<
b100100 S
#1112
0!
0=
#1114
1!
1=
b100100 R
0<
0;
1:
b100101 S
#1116
0!
0=
#1118
1!
1=
b100101 R
1<
b100110 S
#1120
0!
0=
#1122
1!
1=
b100110 R
0<
1;
b100111 S
#1124
0!
0=
#1126
1!
1=
b100111 R
1<
b101000 S
#1128
0!
0=
#1130
1!
1=
b101000 R
0<
0;
0:
19
b101001 S
#1132
0!
0=
#1134
1!
1=
b101001 R
1<
b101010 S
#1136
0!
0=
#1138
1!
1=
b101010 R
0<
1;
b101011 S
#1140
0!
0=
#1142
1!
1=
b101011 R
1<
b101100 S
#1144
0!
0=
#1146
1!
1=
b101100 R
0<
0;
1:
b101101 S
#1148
0!
0=
#1150
1!
1=
b101101 R
1<
b101110 S
#1152
0!
0=
#1154
1!
1=
b101110 R
0<
1;
b101111 S
#1156
0!
0=
#1158
1!
1=
b101111 R
1<
b110000 S
#1160
0!
0=
#1162
1!
1=
b110000 R
0<
0;
0:
09
18
b110001 S
#1164
0!
0=
#1166
1!
1=
b110001 R
1<
b110010 S
#1168
0!
0=
#1170
1!
1=
b110010 R
0<
1;
b110011 S
#1172
0!
0=
#1174
1!
1=
b110011 R
1<
b110100 S
#1176
0!
0=
#1178
1!
1=
b110100 R
0<
0;
1:
b110101 S
#1180
0!
0=
#1182
1!
1=
b110101 R
1<
b110110 S
#1184
0!
0=
#1186
1!
1=
b110110 R
0<
1;
b110111 S
#1188
0!
0=
#1190
1!
1=
b110111 R
1<
b111000 S
#1192
0!
0=
#1194
1!
1=
b111000 R
0<
0;
0:
19
b111001 S
#1196
0!
0=
#1198
1!
1=
b111001 R
1<
b111010 S
#1200
0!
0=
#1202
1!
1=
b111010 R
0<
1;
b111011 S
#1204
0!
0=
#1206
1!
1=
b111011 R
1<
b111100 S
#1208
0!
0=
#1210
1!
1=
b111100 R
0<
0;
1:
b111101 S
#1212
0!
0=
#1214
1!
1=
b111101 R
1<
b111110 S
#1216
0!
0=
#1218
1!
1=
b111110 R
0<
1;
b111111 S
#1220
0!
0=
#1222
1!
1=
b111111 R
1<
b1000000 S
#1224
0!
0=
#1226
1!
1=
b1000000 R
0<
0;
0:
09
08
07
16
b1000001 S
#1228
0!
0=
#1230
1!
1=
b1000001 R
1<
b1000010 S
#1232
0!
0=
#1234
1!
1=
b1000010 R
0<
1;
b1000011 S
#1236
0!
0=
#1238
1!
1=
b1000011 R
1<
b1000100 S
#1240
0!
0=
#1242
1!
1=
b1000100 R
0<
0;
1:
b1000101 S
#1244
0!
0=
#1246
1!
1=
b1000101 R
1<
b1000110 S
#1248
0!
0=
#1250
1!
1=
b1000110 R
0<
1;
b1000111 S
#1252
0!
0=
#1254
1!
1=
b1000111 R
1<
b1001000 S
#1256
0!
0=
#1258
1!
1=
b1001000 R
0<
0;
0:
19
b1001001 S
#1260
0!
0=
#1262
1!
1=
b1001001 R
1<
b1001010 S
#1263
1%
1A
b1001001 S
#1264
0!
0=
#1266
1!
1=
b0 R
0<
09
06
b0 S
